MANIFEST.in
README.md
setup.cfg
setup.py
pandas_zookeeper/__init__.py
pandas_zookeeper/main.py
pandas_zookeeper.egg-info/PKG-INFO
pandas_zookeeper.egg-info/SOURCES.txt
pandas_zookeeper.egg-info/dependency_links.txt
pandas_zookeeper.egg-info/top_level.txt
tests/__init__.py
tests/test_project_datasets.py