Metadata-Version: 2.1
Name: pandas-zookeeper
Version: 0.0.1
Summary: Automate common data cleaning tasks for Pandas Dataframes
Home-page: https://github.com/integral-ssmith/pandas_zookeeper
Author: Shawn Smith
Author-email: ssmith161803@gmail.com
License: UNKNOWN
Platform: UNKNOWN
Classifier: Programming Language :: Python :: 3
Classifier: License :: OSI Approved :: MIT License
Classifier: Operating System :: OS Independent
Requires-Python: >=3.7
